john_prob_distribution
