Metadata-Version: 1.0
Name: john-prob-distribution
Version: 0.4
Summary: Gaussian distributions
Home-page: UNKNOWN
Author: John Amaka
Author-email: UNKNOWN
License: UNKNOWN
Platform: UNKNOWN
